flowhive/__init__.py
flowhive-0.0.2.dist-info/METADATA
flowhive-0.0.2.dist-info/WHEEL
flowhive-0.0.2.dist-info/top_level.txt
flowhive-0.0.2.dist-info/RECORD
