Metadata-Version: 2.2
Name: flowhive
Version: 0.0.2
Summary: Task and Workflow orchestration.
Author-email: Jakob Kristensen <jakob@jakobk.dk>
License: MIT
Requires-Python: >=3.7
